{
"meta":{"test_sets":[],"test_metrics":[],"learn_metrics":[{"best_value":"Min","name":"Logloss"}],"launch_mode":"Train","parameters":"","iteration_count":100,"learn_sets":["learn"],"name":"experiment"},
"iterations":[
{"learn":[0.6836213283],"iteration":0,"passed_time":0.05939424206,"remaining_time":5.880029964},
{"learn":[0.6731834165],"iteration":1,"passed_time":0.05981613387,"remaining_time":2.93099056},
{"learn":[0.6515214771],"iteration":2,"passed_time":0.05995751451,"remaining_time":1.938626302},
{"learn":[0.6436412347],"iteration":3,"passed_time":0.06012343779,"remaining_time":1.442962507},
{"learn":[0.6373614993],"iteration":4,"passed_time":0.06035057184,"remaining_time":1.146660865},
{"learn":[0.6242788809],"iteration":5,"passed_time":0.06059804003,"remaining_time":0.9493692939},
{"learn":[0.6115894591],"iteration":6,"passed_time":0.0607551713,"remaining_time":0.8071758472},
{"learn":[0.5965843729],"iteration":7,"passed_time":0.0609108025,"remaining_time":0.7004742287},
{"learn":[0.5783121005],"iteration":8,"passed_time":0.06101493165,"remaining_time":0.6169287533},
{"learn":[0.5608459505],"iteration":9,"passed_time":0.06109535152,"remaining_time":0.5498581637},
{"learn":[0.5441440368],"iteration":10,"passed_time":0.06117460468,"remaining_time":0.4949581651},
{"learn":[0.5383183341],"iteration":11,"passed_time":0.06133486107,"remaining_time":0.4497889811},
{"learn":[0.5302822821],"iteration":12,"passed_time":0.06152353525,"remaining_time":0.4117344282},
{"learn":[0.5148870865],"iteration":13,"passed_time":0.06161787234,"remaining_time":0.3785097873},
{"learn":[0.5084457459],"iteration":14,"passed_time":0.06174758585,"remaining_time":0.3499029865},
{"learn":[0.4939918419],"iteration":15,"passed_time":0.06183179754,"remaining_time":0.3246169371},
{"learn":[0.485003385],"iteration":16,"passed_time":0.0619998459,"remaining_time":0.30270513},
{"learn":[0.478334483],"iteration":17,"passed_time":0.06217306114,"remaining_time":0.2832328341},
{"learn":[0.4651414225],"iteration":18,"passed_time":0.06225581444,"remaining_time":0.2654063668},
{"learn":[0.4524934589],"iteration":19,"passed_time":0.06235648511,"remaining_time":0.2494259405},
{"learn":[0.4435360918],"iteration":20,"passed_time":0.06246578114,"remaining_time":0.2349903195},
{"learn":[0.4342666332],"iteration":21,"passed_time":0.06257928566,"remaining_time":0.2218720128},
{"learn":[0.4228579951],"iteration":22,"passed_time":0.06265499701,"remaining_time":0.2097580335},
{"learn":[0.4190310535],"iteration":23,"passed_time":0.06280958651,"remaining_time":0.1988970239},
{"learn":[0.4082265176],"iteration":24,"passed_time":0.06291004884,"remaining_time":0.1887301465},
{"learn":[0.4017258257],"iteration":25,"passed_time":0.06308005562,"remaining_time":0.1795355429},
{"learn":[0.3916052536],"iteration":26,"passed_time":0.06315839207,"remaining_time":0.1707615786},
{"learn":[0.381877825],"iteration":27,"passed_time":0.0632417704,"remaining_time":0.1626216953},
{"learn":[0.3725244545],"iteration":28,"passed_time":0.06332952389,"remaining_time":0.1550481447},
{"learn":[0.367317568],"iteration":29,"passed_time":0.06343323636,"remaining_time":0.1480108848},
{"learn":[0.3585162619],"iteration":30,"passed_time":0.06444786013,"remaining_time":0.1434484629},
{"learn":[0.3543866738],"iteration":31,"passed_time":0.06478420687,"remaining_time":0.1376664396},
{"learn":[0.3473756324],"iteration":32,"passed_time":0.06501588277,"remaining_time":0.1320019438},
{"learn":[0.3427283121],"iteration":33,"passed_time":0.06523947501,"remaining_time":0.1266413338},
{"learn":[0.3348421376],"iteration":34,"passed_time":0.06539418951,"remaining_time":0.1214463519},
{"learn":[0.3272425365],"iteration":35,"passed_time":0.06625693223,"remaining_time":0.1177901017},
{"learn":[0.3226856261],"iteration":36,"passed_time":0.06653952682,"remaining_time":0.1132970322},
{"learn":[0.3155230185],"iteration":37,"passed_time":0.06666819862,"remaining_time":0.1087744293},
{"learn":[0.3086136798],"iteration":38,"passed_time":0.06750077346,"remaining_time":0.1055781329},
{"learn":[0.3019461397],"iteration":39,"passed_time":0.06769144773,"remaining_time":0.1015371716},
{"learn":[0.2982541256],"iteration":40,"passed_time":0.06792799882,"remaining_time":0.09775004709},
{"learn":[0.2919440377],"iteration":41,"passed_time":0.06808279666,"remaining_time":0.09401910015},
{"learn":[0.2858490052],"iteration":42,"passed_time":0.06821042675,"remaining_time":0.09041847266},
{"learn":[0.2799595641],"iteration":43,"passed_time":0.06835709926,"remaining_time":0.08699994451},
{"learn":[0.2753729358],"iteration":44,"passed_time":0.06853798147,"remaining_time":0.08376864402},
{"learn":[0.2712699278],"iteration":45,"passed_time":0.06870490479,"remaining_time":0.08065358388},
{"learn":[0.2658578633],"iteration":46,"passed_time":0.06884070187,"remaining_time":0.07762887657},
{"learn":[0.2606221086],"iteration":47,"passed_time":0.06971857018,"remaining_time":0.07552845103},
{"learn":[0.2555551754],"iteration":48,"passed_time":0.06985953414,"remaining_time":0.07271094369},
{"learn":[0.2506499529],"iteration":49,"passed_time":0.06996633006,"remaining_time":0.06996633006},
{"learn":[0.2471365599],"iteration":50,"passed_time":0.07015183745,"remaining_time":0.067400785},
{"learn":[0.2424937236],"iteration":51,"passed_time":0.0702601751,"remaining_time":0.06485554625},
{"learn":[0.2379951112],"iteration":52,"passed_time":0.07036788773,"remaining_time":0.06240171176},
{"learn":[0.2347740923],"iteration":53,"passed_time":0.07050743496,"remaining_time":0.06006188904},
{"learn":[0.2305096796],"iteration":54,"passed_time":0.07059714687,"remaining_time":0.05776130198},
{"learn":[0.2281668596],"iteration":55,"passed_time":0.07074540277,"remaining_time":0.05558567361},
{"learn":[0.2241015218],"iteration":56,"passed_time":0.07085965733,"remaining_time":0.05345553097},
{"learn":[0.2211912679],"iteration":57,"passed_time":0.07102616396,"remaining_time":0.05143273942},
{"learn":[0.2173308251],"iteration":58,"passed_time":0.07112733466,"remaining_time":0.04942746985},
{"learn":[0.2135834262],"iteration":59,"passed_time":0.07122900538,"remaining_time":0.04748600359},
{"learn":[0.2099446722],"iteration":60,"passed_time":0.0713556771,"remaining_time":0.04562084273},
{"learn":[0.2064103705],"iteration":61,"passed_time":0.0714627647,"remaining_time":0.04379975901},
{"learn":[0.2029765245],"iteration":62,"passed_time":0.07155881019,"remaining_time":0.04202660281},
{"learn":[0.1996393229],"iteration":63,"passed_time":0.0717136497,"remaining_time":0.04033892795},
{"learn":[0.1963951297],"iteration":64,"passed_time":0.07182202901,"remaining_time":0.03867340024},
{"learn":[0.1932404752],"iteration":65,"passed_time":0.07270348081,"remaining_time":0.0374533083},
{"learn":[0.1901720469],"iteration":66,"passed_time":0.07356255671,"remaining_time":0.03623230405},
{"learn":[0.1871866818],"iteration":67,"passed_time":0.07371297938,"remaining_time":0.03468846088},
{"learn":[0.184281358],"iteration":68,"passed_time":0.07381960862,"remaining_time":0.03316533141},
{"learn":[0.181453188],"iteration":69,"passed_time":0.07392919633,"remaining_time":0.03168394128},
{"learn":[0.1786994113],"iteration":70,"passed_time":0.07402915864,"remaining_time":0.03023726198},
{"learn":[0.1760173885],"iteration":71,"passed_time":0.07414453824,"remaining_time":0.02883398709},
{"learn":[0.1734045946],"iteration":72,"passed_time":0.0742614179,"remaining_time":0.02746655183},
{"learn":[0.1708586134],"iteration":73,"passed_time":0.07435946347,"remaining_time":0.02612629798},
{"learn":[0.1683771325],"iteration":74,"passed_time":0.07444959206,"remaining_time":0.02481653069},
{"learn":[0.1659579373],"iteration":75,"passed_time":0.07455772137,"remaining_time":0.02354454359},
{"learn":[0.163598907],"iteration":76,"passed_time":0.07467722614,"remaining_time":0.02230618443},
{"learn":[0.1612980094],"iteration":77,"passed_time":0.07478856391,"remaining_time":0.02109421033},
{"learn":[0.159053297],"iteration":78,"passed_time":0.07555309438,"remaining_time":0.02008373395},
{"learn":[0.1568629026],"iteration":79,"passed_time":0.07637775224,"remaining_time":0.01909443806},
{"learn":[0.1547250356],"iteration":80,"passed_time":0.0764930485,"remaining_time":0.01794281385},
{"learn":[0.1526379781],"iteration":81,"passed_time":0.0766075114,"remaining_time":0.01681628299},
{"learn":[0.1506000818],"iteration":82,"passed_time":0.07674443352,"remaining_time":0.0157187394},
{"learn":[0.1486097643],"iteration":83,"passed_time":0.07685864641,"remaining_time":0.01463974217},
{"learn":[0.1466655066],"iteration":84,"passed_time":0.07698198466,"remaining_time":0.01358505612},
{"learn":[0.1447658494],"iteration":85,"passed_time":0.07710023937,"remaining_time":0.01255120176},
{"learn":[0.1429093908],"iteration":86,"passed_time":0.07726749603,"remaining_time":0.0115457178},
{"learn":[0.1410947837],"iteration":87,"passed_time":0.07738433402,"remaining_time":0.01055240919},
{"learn":[0.139320733],"iteration":88,"passed_time":0.07750317209,"remaining_time":0.009579043742},
{"learn":[0.1375859934],"iteration":89,"passed_time":0.07759930092,"remaining_time":0.008622144547},
{"learn":[0.1358893671],"iteration":90,"passed_time":0.07767388723,"remaining_time":0.007682032803},
{"learn":[0.1342297019],"iteration":91,"passed_time":0.07777364121,"remaining_time":0.006762925322},
{"learn":[0.1326058887],"iteration":92,"passed_time":0.07787289516,"remaining_time":0.005861400711},
{"learn":[0.1310168601],"iteration":93,"passed_time":0.0779716491,"remaining_time":0.004976913772},
{"learn":[0.129461588],"iteration":94,"passed_time":0.07806211104,"remaining_time":0.00410853216},
{"learn":[0.1279390825],"iteration":95,"passed_time":0.0781608233,"remaining_time":0.003256700971},
{"learn":[0.1264483899],"iteration":96,"passed_time":0.07824832679,"remaining_time":0.002420051344},
{"learn":[0.1249885909],"iteration":97,"passed_time":0.07835858118,"remaining_time":0.001599154718},
{"learn":[0.1235587997],"iteration":98,"passed_time":0.07846987729,"remaining_time":0.0007926250231},
{"learn":[0.1221581622],"iteration":99,"passed_time":0.07856896457,"remaining_time":0}
]}